README.md
setup.py
fengmm521_blecam/__init__.py
fengmm521_blecam/cmdUtil.py
fengmm521_blecam/demo.py
fengmm521_blecam/queueUtil.py
fengmm521_blecam.egg-info/PKG-INFO
fengmm521_blecam.egg-info/SOURCES.txt
fengmm521_blecam.egg-info/dependency_links.txt
fengmm521_blecam.egg-info/top_level.txt
fengmm521_blecam/_mac/__init__.py
fengmm521_blecam/_windows/__init__.py